advisory_parser/__init__.py
advisory_parser/exceptions.py
advisory_parser/flaw.py
advisory_parser/parser.py
advisory_parser/parsers/__init__.py
advisory_parser/parsers/chrome.py
advisory_parser/parsers/flash.py
advisory_parser/parsers/jenkins.py
advisory_parser/parsers/mysql.py
advisory_parser/parsers/utils.py
advisory_parser-1.13.dist-info/LICENSE
advisory_parser-1.13.dist-info/METADATA
advisory_parser-1.13.dist-info/WHEEL
advisory_parser-1.13.dist-info/top_level.txt
advisory_parser-1.13.dist-info/RECORD
