Metadata-Version: 2.1
Name: advisory-parser
Version: 1.13
Summary: Security flaw parser for upstream security advisories
Home-page: https://github.com/RedHatProductSecurity/advisory-parser
Author: Martin Prpič, Red Hat Product Security
Author-email: secalert@redhat.com
License: LGPLv3+
Keywords: security advisory parser scraper
Classifier: Development Status :: 5 - Production/Stable
Classifier: Intended Audience :: Developers
Classifier: Topic :: Security
Classifier: License :: OSI Approved :: GNU Lesser General Public License v3 or later (LGPLv3+)
Classifier: Programming Language :: Python :: 3
Classifier: Programming Language :: Python :: 3.6
Classifier: Programming Language :: Python :: 3.7
Classifier: Programming Language :: Python :: 3.8
Classifier: Programming Language :: Python :: 3.9
Classifier: Programming Language :: Python :: 3.10
Classifier: Programming Language :: Python :: 3.11
Classifier: Programming Language :: Python :: 3.12
License-File: LICENSE
Requires-Dist: beautifulsoup4 >=4.0.0
Requires-Dist: cvss >=2.0
